odoo/addons/hr_timesheet_sheet_no_create/README.rst
odoo/addons/hr_timesheet_sheet_no_create/__init__.py
odoo/addons/hr_timesheet_sheet_no_create/__manifest__.py
odoo/addons/hr_timesheet_sheet_no_create/i18n/es.po
odoo/addons/hr_timesheet_sheet_no_create/i18n/hr_timesheet_sheet_no_create.pot
odoo/addons/hr_timesheet_sheet_no_create/i18n/it.po
odoo/addons/hr_timesheet_sheet_no_create/readme/CONTRIBUTORS.rst
odoo/addons/hr_timesheet_sheet_no_create/readme/DESCRIPTION.rst
odoo/addons/hr_timesheet_sheet_no_create/static/description/icon.png
odoo/addons/hr_timesheet_sheet_no_create/static/description/index.html
odoo/addons/hr_timesheet_sheet_no_create/views/hr_timesheet_sheet.xml
odoo12_addon_hr_timesheet_sheet_no_create-12.0.1.0.0.99.dev7.dist-info/METADATA
odoo12_addon_hr_timesheet_sheet_no_create-12.0.1.0.0.99.dev7.dist-info/WHEEL
odoo12_addon_hr_timesheet_sheet_no_create-12.0.1.0.0.99.dev7.dist-info/top_level.txt
odoo12_addon_hr_timesheet_sheet_no_create-12.0.1.0.0.99.dev7.dist-info/RECORD
